{"is_source_file": true, "format": "JavaScript", "description": "This file defines a React context and provider for managing notes state, including actions and reducer logic for CRUD operations and filtering within a notes application.", "external_files": ["react"], "external_methods": ["React.createContext", "React.useCallback", "React.useContext", "React.useReducer"], "published": ["NotesProvider", "useNotesContext"], "classes": [], "methods": [{"name": "NotesProvider({ children })", "description": "React component that provides notes state and actions via context.", "scope": "", "scopeKind": ""}, {"name": "useNotesContext()", "description": "Custom hook to access notes context, ensuring it's used within a NotesProvider.", "scope": "", "scopeKind": ""}, {"name": "reducer(state, action)", "scope": "", "scopeKind": "", "description": "unavailable"}], "calls": ["React.createContext", "React.useReducer", "React.useCallback", "React.useContext", "dispatch", "switch", "map", "filter"], "search-terms": ["notesContext", "useReducer", "NotesProvider", "useNotesContext", "reducer function", "notes state management"], "state": 2, "file_id": 24, "knowledge_revision": 53, "git_revision": "", "ctags": [{"_type": "tag", "name": "NotesContext", "path": "/home/kavia/workspace/code-generation/personal-notes-manager-184199-184208/notes_frontend/src/state/notesContext.js", "pattern": "/^const NotesContext = createContext(null);$/", "language": "JavaScript", "kind": "constant"}, {"_type": "tag", "name": "NotesProvider", "path": "/home/kavia/workspace/code-generation/personal-notes-manager-184199-184208/notes_frontend/src/state/notesContext.js", "pattern": "/^export function NotesProvider({ children }) {$/", "language": "JavaScript", "kind": "function", "signature": "({ children })"}, {"_type": "tag", "name": "actions", "path": "/home/kavia/workspace/code-generation/personal-notes-manager-184199-184208/notes_frontend/src/state/notesContext.js", "pattern": "/^  const actions = {$/", "language": "JavaScript", "kind": "class", "scope": "NotesProvider", "scopeKind": "class"}, {"_type": "tag", "name": "createSuccess", "path": "/home/kavia/workspace/code-generation/personal-notes-manager-184199-184208/notes_frontend/src/state/notesContext.js", "pattern": "/^    createSuccess: (note) => dispatch({ type: 'CREATE_SUCCESS', payload: note }),$/", "language": "JavaScript", "kind": "property", "scope": "NotesProvider.actions", "scopeKind": "class"}, {"_type": "tag", "name": "deleteSuccess", "path": "/home/kavia/workspace/code-generation/personal-notes-manager-184199-184208/notes_frontend/src/state/notesContext.js", "pattern": "/^    deleteSuccess: (id) => dispatch({ type: 'DELETE_SUCCESS', id }),$/", "language": "JavaScript", "kind": "property", "scope": "NotesProvider.actions", "scopeKind": "class"}, {"_type": "tag", "name": "error", "path": "/home/kavia/workspace/code-generation/personal-notes-manager-184199-184208/notes_frontend/src/state/notesContext.js", "pattern": "/^  error: null,$/", "language": "JavaScript", "kind": "property", "scope": "initialState", "scopeKind": "class"}, {"_type": "tag", "name": "filter", "path": "/home/kavia/workspace/code-generation/personal-notes-manager-184199-184208/notes_frontend/src/state/notesContext.js", "pattern": "/^  filter: ''$/", "language": "JavaScript", "kind": "property", "scope": "initialState", "scopeKind": "class"}, {"_type": "tag", "name": "initialState", "path": "/home/kavia/workspace/code-generation/personal-notes-manager-184199-184208/notes_frontend/src/state/notesContext.js", "pattern": "/^const initialState = {$/", "language": "JavaScript", "kind": "class"}, {"_type": "tag", "name": "items", "path": "/home/kavia/workspace/code-generation/personal-notes-manager-184199-184208/notes_frontend/src/state/notesContext.js", "pattern": "/^  items: [],$/", "language": "JavaScript", "kind": "property", "scope": "initialState", "scopeKind": "class"}, {"_type": "tag", "name": "loadError", "path": "/home/kavia/workspace/code-generation/personal-notes-manager-184199-184208/notes_frontend/src/state/notesContext.js", "pattern": "/^    loadError: (error) => dispatch({ type: 'LOAD_ERROR', error }),$/", "language": "JavaScript", "kind": "property", "scope": "NotesProvider.actions", "scopeKind": "class"}, {"_type": "tag", "name": "loadStart", "path": "/home/kavia/workspace/code-generation/personal-notes-manager-184199-184208/notes_frontend/src/state/notesContext.js", "pattern": "/^    loadStart: () => dispatch({ type: 'LOAD_START' }),$/", "language": "JavaScript", "kind": "property", "scope": "NotesProvider.actions", "scopeKind": "class"}, {"_type": "tag", "name": "loadSuccess", "path": "/home/kavia/workspace/code-generation/personal-notes-manager-184199-184208/notes_frontend/src/state/notesContext.js", "pattern": "/^    loadSuccess: (items) => dispatch({ type: 'LOAD_SUCCESS', payload: items }),$/", "language": "JavaScript", "kind": "property", "scope": "NotesProvider.actions", "scopeKind": "class"}, {"_type": "tag", "name": "loading", "path": "/home/kavia/workspace/code-generation/personal-notes-manager-184199-184208/notes_frontend/src/state/notesContext.js", "pattern": "/^  loading: false,$/", "language": "JavaScript", "kind": "property", "scope": "initialState", "scopeKind": "class"}, {"_type": "tag", "name": "reducer", "path": "/home/kavia/workspace/code-generation/personal-notes-manager-184199-184208/notes_frontend/src/state/notesContext.js", "pattern": "/^function reducer(state, action) {$/", "language": "JavaScript", "kind": "function", "signature": "(state, action)"}, {"_type": "tag", "name": "select", "path": "/home/kavia/workspace/code-generation/personal-notes-manager-184199-184208/notes_frontend/src/state/notesContext.js", "pattern": "/^    select: (id) => dispatch({ type: 'SELECT', id }),$/", "language": "JavaScript", "kind": "property", "scope": "NotesProvider.actions", "scopeKind": "class"}, {"_type": "tag", "name": "selectedId", "path": "/home/kavia/workspace/code-generation/personal-notes-manager-184199-184208/notes_frontend/src/state/notesContext.js", "pattern": "/^  selectedId: null,$/", "language": "JavaScript", "kind": "property", "scope": "initialState", "scopeKind": "class"}, {"_type": "tag", "name": "setFilter", "path": "/home/kavia/workspace/code-generation/personal-notes-manager-184199-184208/notes_frontend/src/state/notesContext.js", "pattern": "/^    setFilter: (value) => dispatch({ type: 'FILTER', value }),$/", "language": "JavaScript", "kind": "property", "scope": "NotesProvider.actions", "scopeKind": "class"}, {"_type": "tag", "name": "updateSuccess", "path": "/home/kavia/workspace/code-generation/personal-notes-manager-184199-184208/notes_frontend/src/state/notesContext.js", "pattern": "/^    updateSuccess: (note) => dispatch({ type: 'UPDATE_SUCCESS', payload: note }),$/", "language": "JavaScript", "kind": "property", "scope": "NotesProvider.actions", "scopeKind": "class"}, {"_type": "tag", "name": "useNotesContext", "path": "/home/kavia/workspace/code-generation/personal-notes-manager-184199-184208/notes_frontend/src/state/notesContext.js", "pattern": "/^export function useNotesContext() {$/", "language": "JavaScript", "kind": "function", "signature": "()"}], "hash": "f0848076eec80aa2bf0e1d4f0b4b4775", "format-version": 4, "code-base-name": "notes_frontend", "filename": "notes_frontend/src/state/notesContext.js", "fields": [{"name": "createSuccess: (note) => dispatch({ type: 'CREATE_SUCCESS', payload: note }),", "scope": "NotesProvider.actions", "scopeKind": "class", "description": "unavailable"}, {"name": "deleteSuccess: (id) => dispatch({ type: 'DELETE_SUCCESS', id }),", "scope": "NotesProvider.actions", "scopeKind": "class", "description": "unavailable"}, {"name": "error: null,", "scope": "initialState", "scopeKind": "class", "description": "unavailable"}, {"name": "filter: ''", "scope": "initialState", "scopeKind": "class", "description": "unavailable"}, {"name": "items: [],", "scope": "initialState", "scopeKind": "class", "description": "unavailable"}, {"name": "loadError: (error) => dispatch({ type: 'LOAD_ERROR', error }),", "scope": "NotesProvider.actions", "scopeKind": "class", "description": "unavailable"}, {"name": "loadStart: () => dispatch({ type: 'LOAD_START' }),", "scope": "NotesProvider.actions", "scopeKind": "class", "description": "unavailable"}, {"name": "loadSuccess: (items) => dispatch({ type: 'LOAD_SUCCESS', payload: items }),", "scope": "NotesProvider.actions", "scopeKind": "class", "description": "unavailable"}, {"name": "loading: false,", "scope": "initialState", "scopeKind": "class", "description": "unavailable"}, {"name": "select: (id) => dispatch({ type: 'SELECT', id }),", "scope": "NotesProvider.actions", "scopeKind": "class", "description": "unavailable"}, {"name": "selectedId: null,", "scope": "initialState", "scopeKind": "class", "description": "unavailable"}, {"name": "setFilter: (value) => dispatch({ type: 'FILTER', value }),", "scope": "NotesProvider.actions", "scopeKind": "class", "description": "unavailable"}, {"name": "updateSuccess: (note) => dispatch({ type: 'UPDATE_SUCCESS', payload: note }),", "scope": "NotesProvider.actions", "scopeKind": "class", "description": "unavailable"}], "revision_history": [{"53": ""}]}